sinko-0.1.0.dist-info/licenses/LICENSE
source/__init__.py
source/__main__.py
source/backup.py
source/backup_interface.py
source/backup_manager.py
source/file_list_reader.py
source/main.py
sinko-0.1.0.dist-info/METADATA
sinko-0.1.0.dist-info/WHEEL
sinko-0.1.0.dist-info/entry_points.txt
sinko-0.1.0.dist-info/top_level.txt
sinko-0.1.0.dist-info/RECORD
