Metadata-Version: 2.4
Name: sinko
Version: 0.1.0
Summary: A flexible backup tool supporting local and remote backups using rsync and SSH
Author-email: KEJIA <DETONG.KEJI@GMAIL.COM>
License: MIT License
Project-URL: Repository, https://codeberg.org/wizardelf/sinko
Project-URL: Documentation, https://codeberg.org/wizardelf/sinko/src/branch/ling/README.md
Requires-Python: >=3.7
License-File: LICENSE
Requires-Dist: paramiko>=3.5.0
Requires-Dist: python-rsync==0.1.2
Requires-Dist: edn_format>=0.7.5
Provides-Extra: dev
Requires-Dist: pytest>=8.3.3; extra == "dev"
Requires-Dist: mock>=5.1.0; extra == "dev"
Requires-Dist: build>=1.2.2; extra == "dev"
Dynamic: license-file
